rgagui/__init__.py
rgagui/__main__.py
rgagui/inst/__init__.py
rgagui/inst/commands.py
rgagui/inst/communications.py
rgagui/inst/component.py
rgagui/inst/exceptions.py
rgagui/inst/indexcommands.py
rgagui/inst/instrument.py
rgagui/inst/serial_ports.py
rgagui/plots/basescanplot.py
rgagui/plots/timeplot.py
rgagui/task/__init__.py
rgagui/task/callbacks.py
rgagui/task/config.py
rgagui/task/inputs.py
rgagui/task/sessionhandler.py
rgagui/task/task.py
rgagui/task/taskresult.py
rgagui/ui/__init__.py
rgagui/ui/commConnectDlg.py
rgagui/ui/commandTerminal.py
rgagui/ui/deviceinfohandler.py
rgagui/ui/dockhandler.py
rgagui/ui/inputpanel.py
rgagui/ui/qtloghandler.py
rgagui/ui/resource_rc.py
rgagui/ui/signalhandler.py
rgagui/ui/srslogo.jpg
rgagui/ui/stdout.py
rgagui/ui/taskmain.py
rgagui/ui/ui_commConnectDlg.py
rgagui/ui/ui_commandTerminal.py
rgagui/ui/ui_taskmain.py
rgagui/ui/qt/QtCore.py
rgagui/ui/qt/QtGui.py
rgagui/ui/qt/QtWidgets.py
rgagui/ui/qt/__init__.py
rgagui-0.1.3.dist-info/LICENSE.txt
rgagui-0.1.3.dist-info/METADATA
rgagui-0.1.3.dist-info/WHEEL
rgagui-0.1.3.dist-info/entry_points.txt
rgagui-0.1.3.dist-info/top_level.txt
rgagui-0.1.3.dist-info/RECORD
