Metadata-Version: 2.1
Name: rgagui
Version: 0.1.3
Summary: GUI Interface for RGA Instruments and Tasks
Author: Chulhoon Kim
License: MIT license
Keywords: instrument control,data acquisition,data visualization
Classifier: Development Status :: 3 - Alpha
Classifier: Intended Audience :: Science/Research
Classifier: License :: OSI Approved :: MIT License
Classifier: Programming Language :: Python :: 3.7
Classifier: Programming Language :: Python :: 3.8
Classifier: Programming Language :: Python :: 3.9
Classifier: Topic :: Scientific/Engineering
Requires-Python: >=3.7
License-File: LICENSE.txt
Requires-Dist: pyserial (>=3)
Requires-Dist: pyside2
Requires-Dist: matplotlib
